retroflow/__init__.py
retroflow/debug.py
retroflow/edge_drawing.py
retroflow/export.py
retroflow/generator.py
retroflow/layout.py
retroflow/models.py
retroflow/parser.py
retroflow/positioning.py
retroflow/py.typed
retroflow/renderer.py
retroflow/router.py
retroflow/tracer.py
retroflow-0.10.0.dist-info/METADATA
retroflow-0.10.0.dist-info/WHEEL
retroflow-0.10.0.dist-info/licenses/LICENSE
retroflow-0.10.0.dist-info/RECORD
