Metadata-Version: 2.4
Name: retroflow
Version: 0.10.0
Summary: Generate beautiful ASCII and PNG flowcharts from simple text descriptions
Project-URL: Homepage, https://github.com/ronikobrosly/retroflow
Project-URL: Repository, https://github.com/ronikobrosly/retroflow
Project-URL: Issues, https://github.com/ronikobrosly/retroflow/issues
Author-email: Roni Kobrosly <roni.kobrosly@gmail.com>
License: MIT
License-File: LICENSE
Keywords: ascii,cli,diagram,flowchart,graph,visualization
Classifier: Development Status :: 4 - Beta
Classifier: Intended Audience :: Developers
Classifier: License :: OSI Approved :: MIT License
Classifier: Operating System :: OS Independent
Classifier: Programming Language :: Python :: 3
Classifier: Programming Language :: Python :: 3.9
Classifier: Programming Language :: Python :: 3.10
Classifier: Programming Language :: Python :: 3.11
Classifier: Programming Language :: Python :: 3.12
Classifier: Programming Language :: Python :: 3.13
Classifier: Topic :: Software Development :: Libraries :: Python Modules
Classifier: Topic :: Text Processing :: General
Classifier: Typing :: Typed
Requires-Python: >=3.9
Requires-Dist: networkx>=3.0.0
Requires-Dist: pillow>=9.0.0
